azure/mgmt/servicefabricmanagedclusters/__init__.py
azure/mgmt/servicefabricmanagedclusters/_configuration.py
azure/mgmt/servicefabricmanagedclusters/_patch.py
azure/mgmt/servicefabricmanagedclusters/_serialization.py
azure/mgmt/servicefabricmanagedclusters/_service_fabric_managed_clusters_management_client.py
azure/mgmt/servicefabricmanagedclusters/_vendor.py
azure/mgmt/servicefabricmanagedclusters/_version.py
azure/mgmt/servicefabricmanagedclusters/py.typed
azure/mgmt/servicefabricmanagedclusters/aio/__init__.py
azure/mgmt/servicefabricmanagedclusters/aio/_configuration.py
azure/mgmt/servicefabricmanagedclusters/aio/_patch.py
azure/mgmt/servicefabricmanagedclusters/aio/_service_fabric_managed_clusters_management_client.py
azure/mgmt/servicefabricmanagedclusters/aio/operations/__init__.py
azure/mgmt/servicefabricmanagedclusters/aio/operations/_application_type_versions_operations.py
azure/mgmt/servicefabricmanagedclusters/aio/operations/_application_types_operations.py
azure/mgmt/servicefabricmanagedclusters/aio/operations/_applications_operations.py
azure/mgmt/servicefabricmanagedclusters/aio/operations/_managed_apply_maintenance_window_operations.py
azure/mgmt/servicefabricmanagedclusters/aio/operations/_managed_az_resiliency_status_operations.py
azure/mgmt/servicefabricmanagedclusters/aio/operations/_managed_cluster_version_operations.py
azure/mgmt/servicefabricmanagedclusters/aio/operations/_managed_clusters_operations.py
azure/mgmt/servicefabricmanagedclusters/aio/operations/_managed_maintenance_window_status_operations.py
azure/mgmt/servicefabricmanagedclusters/aio/operations/_managed_unsupported_vm_sizes_operations.py
azure/mgmt/servicefabricmanagedclusters/aio/operations/_node_type_skus_operations.py
azure/mgmt/servicefabricmanagedclusters/aio/operations/_node_types_operations.py
azure/mgmt/servicefabricmanagedclusters/aio/operations/_operation_results_operations.py
azure/mgmt/servicefabricmanagedclusters/aio/operations/_operation_status_operations.py
azure_mgmt_servicefabricmanagedclusters-2.0.0.dist-info/LICENSE
azure_mgmt_servicefabricmanagedclusters-2.0.0.dist-info/METADATA
azure_mgmt_servicefabricmanagedclusters-2.0.0.dist-info/WHEEL
azure_mgmt_servicefabricmanagedclusters-2.0.0.dist-info/top_level.txt
azure_mgmt_servicefabricmanagedclusters-2.0.0.dist-info/RECORD
